delve/__init__.py
delve/delve.py
delve_fs-0.1.6.dist-info/licenses/LICENSE
delve_fs-0.1.6.dist-info/METADATA
delve_fs-0.1.6.dist-info/WHEEL
delve_fs-0.1.6.dist-info/top_level.txt
delve_fs-0.1.6.dist-info/RECORD
