Metadata-Version: 2.4
Name: delve-fs
Version: 0.1.6
Summary: Feature selection for preserving biological trajectories from single-cell data
Home-page: https://github.com/jranek/delve
Author: Jolene Ranek
Author-email: ranekjs@gmail.com
License: MIT
Keywords: trajectory inference,feature selection,single-cell bioinformatics,computational biology
Classifier: Development Status :: 3 - Alpha
Classifier: Intended Audience :: Science/Research
Classifier: Topic :: Scientific/Engineering :: Bio-Informatics
Classifier: License :: OSI Approved :: MIT License
Classifier: Programming Language :: Python :: 3.9
Classifier: Operating System :: OS Independent
Requires-Python: ==3.9.*
License-File: LICENSE
Requires-Dist: anndata>=0.7.6
Requires-Dist: sketchKH==0.1.2
Requires-Dist: numpy==1.26.4
Requires-Dist: scipy>=1.7.1
Requires-Dist: pandas==1.5.2
Requires-Dist: scikit-learn>=0.23.2
Requires-Dist: umap-learn==0.5.1
Requires-Dist: matplotlib==3.7.1
Requires-Dist: tqdm
Dynamic: author
Dynamic: author-email
Dynamic: classifier
Dynamic: description
Dynamic: description-content-type
Dynamic: home-page
Dynamic: keywords
Dynamic: license
Dynamic: license-file
Dynamic: requires-dist
Dynamic: requires-python
Dynamic: summary
